armory/__init__.py
armory/__main__.py
armory/armory.py
armory/armory_interactive.py
armory/shell.py
armory/database/Readme.md
armory/database/__init__.py
armory/database/repositories.py
armory/database/models/__init__.py
armory/database/models/basedomain.py
armory/database/models/cidr.py
armory/database/models/cred.py
armory/database/models/cve.py
armory/database/models/domain.py
armory/database/models/ipaddress.py
armory/database/models/port.py
armory/database/models/scopecidr.py
armory/database/models/url.py
armory/database/models/user.py
armory/database/models/vulnerability.py
armory/default_configs/__init__.py
armory/default_configs/settings.ini.default
armory/included/ModuleTemplate.py
armory/included/ReportTemplate.py
armory/included/__init__.py
armory/included/modules/AquatoneDiscover.py
armory/included/modules/AquatoneTakeover.py
armory/included/modules/DNSRecon.py
armory/included/modules/Fierce.py
armory/included/modules/GobusterDNS.py
armory/included/modules/GobusterDir.py
armory/included/modules/Gowitness.py
armory/included/modules/HeaderScanner.py
armory/included/modules/Hydra.py
armory/included/modules/Ingestor.py
armory/included/modules/JexBoss.py
armory/included/modules/LinkedInt.py
armory/included/modules/Nessus.py
armory/included/modules/Nikto.py
armory/included/modules/Nmap.py
armory/included/modules/PowerMeta.py
armory/included/modules/PyMeta.py
armory/included/modules/SSLScan.py
armory/included/modules/SampleModule.py
armory/included/modules/SampleToolModule.py
armory/included/modules/ShodanImport.py
armory/included/modules/Subfinder.py
armory/included/modules/Sublist3r.py
armory/included/modules/TheHarvester.py
armory/included/modules/Tko-subs.py
armory/included/modules/URLScanner.py
armory/included/modules/Whois.py
armory/included/modules/Xsscrapy.py
armory/included/modules/__init__.py
armory/included/reports/ADUserCreds.py
armory/included/reports/CertReport.py
armory/included/reports/CidrReport.py
armory/included/reports/DomainOwnerReport.py
depth_armory-1.0.0.dist-info/LICENSE
depth_armory-1.0.0.dist-info/METADATA
depth_armory-1.0.0.dist-info/WHEEL
depth_armory-1.0.0.dist-info/entry_points.txt
depth_armory-1.0.0.dist-info/top_level.txt
depth_armory-1.0.0.dist-info/RECORD
