Metadata-Version: 2.1
Name: depth-armory
Version: 1.0.0
Summary: Armory is a tool meant to take in a lot of external and discovery data from a lot of tools, add it to a database and correlate all of related information.
Home-page: https://github.com/depthsecurity/armory
Author: Depth Security
Author-email: info@depthsecurity.com
License: UNKNOWN
Keywords: pentesting security
Platform: UNKNOWN
Classifier: Development Status :: 5 - Production/Stable
Classifier: Intended Audience :: Information Technology
Classifier: Intended Audience :: System Administrators
Classifier: Programming Language :: Python :: 3
Classifier: Programming Language :: Python :: 3.3
Classifier: Programming Language :: Python :: 3.4
Classifier: Programming Language :: Python :: 3.5
Classifier: Programming Language :: Python :: 3.6
Requires-Dist: configparser
Requires-Dist: sqlalchemy
Requires-Dist: sqlalchemy-mixins
Requires-Dist: tld
Requires-Dist: dnspython
Requires-Dist: netaddr
Requires-Dist: pyperclip
Requires-Dist: requests
Requires-Dist: ipwhois
Requires-Dist: whois
Requires-Dist: fuzzywuzzy[speedup]
Requires-Dist: xmltodict
Requires-Dist: bs4
Requires-Dist: thready
Requires-Dist: argcomplete
Requires-Dist: tldextract
Requires-Dist: ipaddr
Requires-Dist: mysqlclient
Requires-Dist: lxml
Requires-Dist: IPython (<6.0,>5.0) ; python_version < "3.1"
Requires-Dist: subprocess32 ; python_version < "3.3"
Requires-Dist: IPython ; python_version > "3.1"
Provides-Extra: dev
Requires-Dist: check-manifest ; extra == 'dev'
Requires-Dist: tox ; extra == 'dev'
Provides-Extra: test
Requires-Dist: coverage ; extra == 'test'
Requires-Dist: mock ; (python_version < "3.4") and extra == 'test'
